pymlsql/__init__.py
pymlsql/build_mlsql_server.py
pymlsql/cli.py
pymlsql/test.py
pymlsql/version.py
pymlsql/aliyun/__init__.py
pymlsql/aliyun/build_test_server.py
pymlsql/aliyun/ecs_builder.py
pymlsql/aliyun/shellutils.py
pymlsql/aliyun/dev/__init__.py
pymlsql/aliyun/dev/copy_from_local.py
pymlsql/aliyun/dev/copy_to_local.py
pymlsql/aliyun/dev/instance_context.py
pymlsql/aliyun/dev/oss_context.py
pymlsql/aliyun/dev/run_remote_shell.py
pymlsql/aliyun/dev/start_server.py
pymlsql/aliyun/dev/stop_realse_server.py
pymlsql/api/__init__.py
pymlsql/api/mlsql_context.py
pymlsql/utils/__init__.py
pymlsql/utils/click_args.py
pymlsql-1.1.6.3.dist-info/LICENSE.txt
pymlsql-1.1.6.3.dist-info/METADATA
pymlsql-1.1.6.3.dist-info/WHEEL
pymlsql-1.1.6.3.dist-info/entry_points.txt
pymlsql-1.1.6.3.dist-info/top_level.txt
pymlsql-1.1.6.3.dist-info/RECORD
